linkiq/.DS_Store
linkiq/__init__.py
linkiq/linkiq.py
linkiq/agent/__init__.py
linkiq/agent/lead_scorer.py
linkiq/agent/llm_utils.py
linkiq/agent/note_generator.py
linkiq/controller/__init__.py
linkiq/controller/campaign_handler.py
linkiq/controller/li_handler.py
linkiq/controller/message_handler.py
linkiq/controller/post_handler.py
linkiq/controller/profile_handler.py
linkiq/controller/reaction_handler.py
linkiq/controller/scheduler.py
linkiq/controller/search_handler.py
linkiq/controller/view_handler.py
linkiq/model/__init__.py
linkiq/model/db_client.py
linkiq/model/lead.py
linkiq/model/post.py
linkiq/model/profile.py
linkiq/model/queue.py
linkiq/model/schedule.py
linkiq/utils/__init__.py
linkiq/utils/page.py
linkiq/view/.DS_Store
linkiq/view/__init__.py
linkiq/view/api.py
linkiq/view/static/.DS_Store
linkiq/view/static/favicon.png
linkiq/view/static/index.html
linkiq/view/static/placeholder.svg
linkiq/view/static/robots.txt
linkiq/view/static/assets/index-B9ykfSDz.css
linkiq/view/static/assets/index-HkwdDS5m.js
linkiq-0.9.0.dist-info/licenses/LICENSE
linkiq-0.9.0.dist-info/METADATA
linkiq-0.9.0.dist-info/WHEEL
linkiq-0.9.0.dist-info/entry_points.txt
linkiq-0.9.0.dist-info/top_level.txt
linkiq-0.9.0.dist-info/RECORD
